gettex/__init__.py
gettex/exceptions.py
gettex/logging.py
gettex/msgfmt.py
gettex/po_header.py
gettex/po_renderer.py
gettex/sty_renderer.py
gettex/xgettext.py
gettex/parsers/__init__.py
gettex/parsers/latex.py
gettex-1.0.dist-info/LICENSE.md
gettex-1.0.dist-info/METADATA
gettex-1.0.dist-info/WHEEL
gettex-1.0.dist-info/entry_points.txt
gettex-1.0.dist-info/top_level.txt
gettex-1.0.dist-info/RECORD
