Metadata-Version: 2.1
Name: gettex
Version: 1.0
Summary: Helper to use gettext on tex files
Author: Fabian Kreutz
Author-email: project+gettex@fabian-kreutz.de
License: MIT
Classifier: Programming Language :: Python :: 3
License-File: LICENSE.md
